[
  {
    "accountId": { "accountExternalKey": { "mnemonic": "CHINA" } },
    "orderTypeCode": "Market",
    "quantity": 100,
    "securityId": { "securityFigiKey": { "figi": "BBG000BCZFG1" } },
    "sideCode": "Buy",
    "timeInForceCode": "Day"
  },
  {
    "accountId": { "accountExternalKey": { "mnemonic": "CHINA" } },
    "orderTypeCode": "Market",
    "quantity": 34111,
    "securityId": { "securityExternalKey": { "externalId": "USD" } },
    "sideCode": "Sell",
    "timeInForceCode": "Day"
  }
]